anisearch/AniSearch.py
anisearch/__init__.py
anisearch/cli.py
anisearch/plugins/Anime.py
anisearch/plugins/__init__.py
anisearch/plugins/_webget.py
anisearch/plugins/_webget_cf.py
anisearch/plugins/acgrip.py
anisearch/plugins/comicat.py
anisearch/plugins/dmhy.py
anisearch/plugins/kisssub.py
anisearch/plugins/miobt.py
anisearch/plugins/nyaa.py
anisearch/plugins/tokyotosho.py
Anisearch_lib-1.4.0.dist-info/LICENSE
Anisearch_lib-1.4.0.dist-info/METADATA
Anisearch_lib-1.4.0.dist-info/WHEEL
Anisearch_lib-1.4.0.dist-info/entry_points.txt
Anisearch_lib-1.4.0.dist-info/top_level.txt
Anisearch_lib-1.4.0.dist-info/RECORD
