Metadata-Version: 2.1
Name: Anisearch-lib
Version: 1.4.0
Summary: A library for searching anime magnet links
Home-page: https://anisearch.mmoe.work
Author: adogecheems
Author-email: adogecheems@outlook.com
License: AGPLv3
Keywords: search download magnet link magnet-link torrent anime dmhy comicat kisssub miobt nyaa acg.rip acgrip tokyotosho cli commandline
Classifier: Development Status :: 5 - Production/Stable
Classifier: License :: OSI Approved :: GNU Affero General Public License v3
Classifier: Programming Language :: Python :: 3
Classifier: Programming Language :: Python :: 3.6
Classifier: Programming Language :: Python :: 3.7
Classifier: Programming Language :: Python :: 3.8
Classifier: Programming Language :: Python :: 3.9
Classifier: Programming Language :: Python :: 3.10
Classifier: Programming Language :: Python :: 3.11
Classifier: Programming Language :: Python :: 3.12
License-File: LICENSE
Requires-Dist: rich
Requires-Dist: bs4
Requires-Dist: lxml
Requires-Dist: requests
